torch_npu-2.6.0.dist-info/WHEEL
torch_npu-2.6.0.dist-info/METADATA
torch_npu-2.6.0.dist-info/entry_points.txt
torch_npu-2.6.0.dist-info/RECORD
torch_npu-2.6.0.dist-info/LICENSE
torch_npu-2.6.0.dist-info/top_level.txt
torch_npu/__init__.py
torch_npu/_C.cpython-310-x86_64-linux-gnu.so
torch_npu/acl.json
torch_npu/_op_plugin_docs.py
torch_npu/version.py
torch_npu/onnx/__init__.py
torch_npu/onnx/wrapper_ops_combined.py
torch_npu/onnx/wrapper_onnx_ops.py
torch_npu/dynamo/__init__.py
torch_npu/dynamo/torchair/npu_fx_compiler.py
torch_npu/dynamo/torchair/fx_dumper.py
torch_npu/dynamo/torchair/__init__.py
torch_npu/dynamo/torchair/npu_export.py
torch_npu/dynamo/torchair/fx_summary.py
torch_npu/dynamo/torchair/core/_abi_compat_ge_apis.so
torch_npu/dynamo/torchair/core/_concrete_graph.py
torch_npu/dynamo/torchair/core/_npu_graph_executor.so
torch_npu/dynamo/torchair/core/_torchair.so
torch_npu/dynamo/torchair/core/utils.py
torch_npu/dynamo/torchair/core/_backend.py
torch_npu/dynamo/torchair/_acl_concrete_graph/fx2acl_converter.py
torch_npu/dynamo/torchair/_acl_concrete_graph/graph_pass.py
torch_npu/dynamo/torchair/_acl_concrete_graph/acl_graph.py
torch_npu/dynamo/torchair/_utils/adjust_traceable_collective_remaps.py
torch_npu/dynamo/torchair/_utils/__init__.py
torch_npu/dynamo/torchair/_utils/error_code.py
torch_npu/dynamo/torchair/_utils/custom_aot_functions.py
torch_npu/dynamo/torchair/_utils/path_manager.py
torch_npu/dynamo/torchair/_utils/adjust_implicit_decomposition.py
torch_npu/dynamo/torchair/_utils/export_utils.py
torch_npu/dynamo/torchair/_utils/npu_fx_passes/joint_graph.py
torch_npu/dynamo/torchair/_utils/npu_fx_passes/joint_graph_passes/npu_rotary_mul.py
torch_npu/dynamo/torchair/_utils/npu_fx_passes/joint_graph_passes/npu_rms_norm.py
torch_npu/dynamo/torchair/_utils/npu_fx_passes/joint_graph_passes/__init__.py
torch_npu/dynamo/torchair/_utils/npu_fx_passes/joint_graph_passes/npu_fusion_attention.py
torch_npu/dynamo/torchair/_ge_concrete_graph/export_config_generete.py
torch_npu/dynamo/torchair/_ge_concrete_graph/ge_ir_pb2.py
torch_npu/dynamo/torchair/_ge_concrete_graph/graph_pass.py
